effectful/__init__.py
effectful/py.typed
effectful/handlers/__init__.py
effectful/handlers/indexed.py
effectful/handlers/numpyro.py
effectful/handlers/pyro.py
effectful/handlers/torch.py
effectful/handlers/jax/__init__.py
effectful/handlers/jax/_handlers.py
effectful/handlers/jax/_terms.py
effectful/handlers/jax/numpy/__init__.py
effectful/handlers/jax/numpy/linalg.py
effectful/handlers/jax/scipy/special.py
effectful/handlers/llm/__init__.py
effectful/handlers/llm/completions.py
effectful/handlers/llm/encoding.py
effectful/handlers/llm/synthesis.py
effectful/handlers/llm/template.py
effectful/internals/__init__.py
effectful/internals/product_n.py
effectful/internals/runtime.py
effectful/internals/tensor_utils.py
effectful/internals/unification.py
effectful/ops/__init__.py
effectful/ops/semantics.py
effectful/ops/syntax.py
effectful/ops/types.py
effectful-0.3.0.dist-info/licenses/LICENSE.md
effectful-0.3.0.dist-info/METADATA
effectful-0.3.0.dist-info/WHEEL
effectful-0.3.0.dist-info/top_level.txt
effectful-0.3.0.dist-info/RECORD
