Metadata-Version: 2.4
Name: effectful
Version: 0.3.0
Summary: Metaprogramming infrastructure
Author: Basis
License-Expression: Apache-2.0
Project-URL: Homepage, https://www.basis.ai/
Project-URL: Source, https://github.com/BasisResearch/effectful
Project-URL: Bug Tracker, https://github.com/BasisResearch/effectful/issues
Keywords: machine learning,statistics,probabilistic programming,bayesian modeling,pytorch
Classifier: Intended Audience :: Developers
Classifier: Intended Audience :: Education
Classifier: Intended Audience :: Science/Research
Classifier: Operating System :: POSIX :: Linux
Classifier: Operating System :: MacOS :: MacOS X
Classifier: Programming Language :: Python :: 3.12
Classifier: Programming Language :: Python :: 3.13
Requires-Python: <3.14,>=3.12
License-File: LICENSE.md
Provides-Extra: torch
Requires-Dist: torch; extra == "torch"
Provides-Extra: pyro
Requires-Dist: pyro-ppl>=1.9.1; extra == "pyro"
Provides-Extra: jax
Requires-Dist: jax; extra == "jax"
Provides-Extra: numpyro
Requires-Dist: numpyro>=0.19; extra == "numpyro"
Provides-Extra: llm
Requires-Dist: litellm; extra == "llm"
Requires-Dist: pillow; extra == "llm"
Requires-Dist: pydantic; extra == "llm"
Provides-Extra: prettyprinter
Requires-Dist: prettyprinter; extra == "prettyprinter"
Provides-Extra: docs
Requires-Dist: effectful[jax,llm,numpyro,prettyprinter,pyro,torch]; extra == "docs"
Requires-Dist: sphinx; extra == "docs"
Requires-Dist: sphinxcontrib-bibtex; extra == "docs"
Requires-Dist: sphinx_rtd_theme; extra == "docs"
Requires-Dist: myst-parser; extra == "docs"
Requires-Dist: nbsphinx; extra == "docs"
Requires-Dist: sphinx_autodoc_typehints; extra == "docs"
Requires-Dist: pypandoc_binary<1.16; extra == "docs"
Provides-Extra: test
Requires-Dist: effectful[docs,jax,numpyro,prettyprinter,pyro,torch]; extra == "test"
Requires-Dist: pytest; extra == "test"
Requires-Dist: pytest-cov; extra == "test"
Requires-Dist: pytest-xdist; extra == "test"
Requires-Dist: pytest-benchmark; extra == "test"
Requires-Dist: mypy; extra == "test"
Requires-Dist: ruff; extra == "test"
Requires-Dist: nbval; extra == "test"
Requires-Dist: nbqa; extra == "test"
Dynamic: license-file
